{"nodes": [{"id": "c_avihusitton_therapy_new_build_cf_sh", "label": "build-cf.sh", "file_type": "code", "source_file": "C:\\Avihusitton\\therapy_new\\build-cf.sh", "source_location": "L1", "metadata": {"language": "bash", "kind": "file"}}, {"id": "c_avihusitton_therapy_new_build_cf_sh__entry", "label": "build-cf.sh script", "file_type": "code", "source_file": "C:\\Avihusitton\\therapy_new\\build-cf.sh", "source_location": "L1", "metadata": {"language": "bash", "kind": "bash_entrypoint"}}], "edges": [{"source": "c_avihusitton_therapy_new_build_cf_sh", "target": "c_avihusitton_therapy_new_build_cf_sh__entry", "relation": "contains", "confidence": "EXTRACTED", "source_file": "C:\\Avihusitton\\therapy_new\\build-cf.sh", "source_location": "L1", "weight": 1.0}]}